pyeqeq_eqeq.cpython-38-darwin.so
pyeqeq/__init__.py
pyeqeq/cli.py
pyeqeq/main.py
pyeqeq/settings.py
pyeqeq/version.py
pyeqeq/data/chargecenters.dat
pyeqeq/data/ionizationdata.dat
pyeqeq-0.0.10.data/headers/main.h
pyeqeq-0.0.10.dist-info/LICENSE
pyeqeq-0.0.10.dist-info/METADATA
pyeqeq-0.0.10.dist-info/WHEEL
pyeqeq-0.0.10.dist-info/entry_points.txt
pyeqeq-0.0.10.dist-info/top_level.txt
pyeqeq-0.0.10.dist-info/RECORD
