Metadata-Version: 2.1
Name: pyeqeq
Version: 0.0.10
Summary: Charge equilibration method for crystal structures
Home-page: https://github.com/lsmo-epfl/EQeq
Author: EQeq developers
Author-email: kevin.jablonka@epfl.ch
License: GPL
Classifier: Programming Language :: Python :: 3
Classifier: Programming Language :: Python :: 3 :: Only
Classifier: Programming Language :: Python :: 3.7
Classifier: Programming Language :: Python :: 3.8
Classifier: Development Status :: 4 - Beta
Classifier: Intended Audience :: Science/Research
Classifier: Operating System :: OS Independent
Classifier: Topic :: Scientific/Engineering
Classifier: Topic :: Scientific/Engineering :: Physics
Classifier: Topic :: Scientific/Engineering :: Chemistry
Classifier: Topic :: Software Development :: Libraries :: Python Modules
Requires-Python: >=3.7
License-File: LICENSE
Requires-Dist: pybind11
Requires-Dist: click
